minecraft_backup/backup.py
minecraft_backup/util.py
mcbackup-0.4.2.dist-info/LICENSE.txt
mcbackup-0.4.2.dist-info/METADATA
mcbackup-0.4.2.dist-info/WHEEL
mcbackup-0.4.2.dist-info/entry_points.txt
mcbackup-0.4.2.dist-info/RECORD
